{
  "generated_at": "2026-04-16",
  "analysis_window": "18 months",
  "criteria": {
    "min_llc_entities": 2,
    "min_acquisitions": 5,
    "high_displacement_score_threshold": 40
  },
  "operators_found": 20,
  "operators": [
    {
      "operator_root": "OCEANVIEW",
      "total_properties": 128,
      "total_acquisitions": 128,
      "llc_count": 2,
      "llc_entities": [
        "OCEANVIEW LIFE AN ANNUITY COMPANY",
        "OCEANVIEW LIFE AND ANNUITY COMPANY"
      ],
      "total_portfolio_value": 0,
      "avg_acquisition_price": 0.0,
      "acquisitions_per_month": 24.94,
      "first_acquisition": "2025-04-29",
      "last_acquisition": "2025-09-30",
      "zip_codes_targeted": [
        "10012",
        "10013",
        "10014",
        "10017",
        "10018",
        "10027",
        "10030",
        "10451",
        "10453",
        "10454",
        "10455",
        "10456",
        "10457",
        "10458",
        "10459",
        "10461",
        "10465",
        "10467",
        "10468",
        "10469",
        "10470",
        "10472",
        "11104",
        "11201",
        "11206",
        "11207",
        "11209",
        "11211",
        "11212",
        "11213",
        "11216",
        "11221",
        "11222",
        "11226",
        "11231",
        "11233",
        "11234",
        "11235",
        "11237",
        "11238",
        "11366",
        "11367",
        "11373",
        "11385",
        "11415",
        "11418",
        "11423",
        "11428",
        "11691"
      ],
      "high_displacement_acquisitions": 71,
      "high_displacement_pct": 55.5,
      "targets_high_displacement": true
    },
    {
      "operator_root": "CHURCHILL",
      "total_properties": 86,
      "total_acquisitions": 159,
      "llc_count": 5,
      "llc_entities": [
        "CHURCHILL DANIELE",
        "CHURCHILL FUNDING I LLC",
        "CHURCHILL MARA FUNDING I LLC",
        "CHURCHILL MRA FUNDING I LLC",
        "FB CHURCHILL FACILITY LLC"
      ],
      "total_portfolio_value": 2185000.0,
      "avg_acquisition_price": 13742.14,
      "acquisitions_per_month": 14.68,
      "first_acquisition": "2025-04-29",
      "last_acquisition": "2026-03-20",
      "zip_codes_targeted": [
        "10001",
        "10003",
        "10009",
        "10011",
        "10013",
        "10019",
        "10026",
        "10035",
        "10038",
        "10452",
        "10455",
        "10456",
        "10458",
        "10461",
        "10465",
        "10468",
        "11101",
        "11104",
        "11201",
        "11205",
        "11206",
        "11211",
        "11212",
        "11213",
        "11215",
        "11216",
        "11221",
        "11222",
        "11223",
        "11225",
        "11226",
        "11231",
        "11232",
        "11233",
        "11249",
        "11368",
        "11369",
        "11433"
      ],
      "high_displacement_acquisitions": 62,
      "high_displacement_pct": 39.0,
      "targets_high_displacement": false
    },
    {
      "operator_root": "ICECAP",
      "total_properties": 73,
      "total_acquisitions": 145,
      "llc_count": 7,
      "llc_entities": [
        "ICECAP FUND III SPV-C LLC",
        "ICECAP REAL",
        "ICECAP REAL ESTATE DEBT FUND 111 LLC",
        "ICECAP REAL ESTATE DEBT FUND IHI LLC",
        "ICECAP REAL ESTATE DEBT FUND III LLC",
        "ICECAP SUB-REIT SPV I LLC",
        "ICECAP SUB-REIT SPV-I LLC"
      ],
      "total_portfolio_value": 0,
      "avg_acquisition_price": 0.0,
      "acquisitions_per_month": 12.95,
      "first_acquisition": "2025-04-15",
      "last_acquisition": "2026-03-17",
      "zip_codes_targeted": [
        "10027",
        "10453",
        "10456",
        "10457",
        "10459",
        "10466",
        "10467",
        "10468",
        "10469",
        "10472",
        "10474",
        "11206",
        "11208",
        "11212",
        "11213",
        "11219",
        "11221",
        "11225",
        "11226",
        "11231"
      ],
      "high_displacement_acquisitions": 54,
      "high_displacement_pct": 37.2,
      "targets_high_displacement": false
    },
    {
      "operator_root": "BREDIF",
      "total_properties": 66,
      "total_acquisitions": 67,
      "llc_count": 3,
      "llc_entities": [
        "BREDIF CO SELLER LLC",
        "BREDIF JPM SELLER LLC",
        "BREDIF LPA LLC"
      ],
      "total_portfolio_value": 0,
      "avg_acquisition_price": 0.0,
      "acquisitions_per_month": 9.44,
      "first_acquisition": "2025-06-10",
      "last_acquisition": "2026-01-09",
      "zip_codes_targeted": [
        "10001",
        "10002",
        "10010",
        "10011",
        "10016",
        "10022",
        "10028",
        "10036",
        "10038",
        "10451",
        "10454",
        "10455",
        "10457",
        "10461",
        "10467",
        "11040",
        "11201",
        "11205",
        "11206",
        "11211",
        "11212",
        "11215",
        "11216",
        "11217",
        "11220",
        "11221",
        "11222",
        "11225",
        "11237",
        "11238",
        "11368",
        "11374",
        "11375",
        "11385",
        "11412",
        "11417",
        "11433"
      ],
      "high_displacement_acquisitions": 25,
      "high_displacement_pct": 37.3,
      "targets_high_displacement": false
    },
    {
      "operator_root": "TOORAK",
      "total_properties": 65,
      "total_acquisitions": 99,
      "llc_count": 2,
      "llc_entities": [
        "TOORAK CAPITAL PARTNERS",
        "TOORAK CAPITAL PARTNERS LLC"
      ],
      "total_portfolio_value": 0,
      "avg_acquisition_price": 0.0,
      "acquisitions_per_month": 9.05,
      "first_acquisition": "2025-04-15",
      "last_acquisition": "2026-03-09",
      "zip_codes_targeted": [
        "10022",
        "10453",
        "10455",
        "10459",
        "10460",
        "10466",
        "10467",
        "11102",
        "11204",
        "11205",
        "11210",
        "11211",
        "11212",
        "11213",
        "11215",
        "11221",
        "11225",
        "11230",
        "11231",
        "11238",
        "11368",
        "11691"
      ],
      "high_displacement_acquisitions": 35,
      "high_displacement_pct": 35.4,
      "targets_high_displacement": false
    },
    {
      "operator_root": "PHANTOM",
      "total_properties": 64,
      "total_acquisitions": 65,
      "llc_count": 32,
      "llc_entities": [
        "PHANTOM & Z CAPITAL LLC",
        "PHANTOM AFFORDABLE HOUSING LLC",
        "PHANTOM CAP HOLDINGS 206 LLC",
        "PHANTOM CAP MAP LLC",
        "PHANTOM CAPITAL 10 LLC",
        "PHANTOM CAPITAL 107 LLC",
        "PHANTOM CAPITAL 11 LLC",
        "PHANTOM CAPITAL 12 LLC",
        "PHANTOM CAPITAL 161 LLC",
        "PHANTOM CAPITAL 21 LLC",
        "PHANTOM CAPITAL 22 LLC",
        "PHANTOM CAPITAL 350 LLC",
        "PHANTOM CAPITAL 44 LLC",
        "PHANTOM CAPITAL 53 LLC",
        "PHANTOM CAPITAL 55 LLC",
        "PHANTOM CAPITAL 71 LLC",
        "PHANTOM CAPITAL 800 LLC",
        "PHANTOM CAPITAL ACQUISITIONS LLC",
        "PHANTOM CAPITAL BX LLC",
        "PHANTOM HOUSING LLC",
        "PHANTOM KOACH LLC",
        "PHANTOM LANDLORDS LLC",
        "PHANTOM NYC HOLDINGS LLC",
        "PHANTOM PARTNERS 89 LLC",
        "PHANTOM PARTNERS BH LLC",
        "PHANTOM PARTNERS PROPERTIES LLC",
        "PHANTOM PARTNERS RE LLC",
        "PHANTOM RISE LLC",
        "PHANTOM TERRITORY LLC",
        "PHANTOM TITANS LLC",
        "PHANTOM TOWN LLC",
        "PHANTOM TROPHIES LLC"
      ],
      "total_portfolio_value": 49898000.0,
      "avg_acquisition_price": 767661.54,
      "acquisitions_per_month": 6.19,
      "first_acquisition": "2025-05-01",
      "last_acquisition": "2026-03-12",
      "zip_codes_targeted": [
        "10454",
        "10455",
        "10456",
        "10457",
        "10459",
        "10460",
        "10462",
        "10466",
        "10467",
        "10469",
        "10470",
        "10472",
        "10473",
        "10474",
        "11207",
        "11210",
        "11212",
        "11421"
      ],
      "high_displacement_acquisitions": 29,
      "high_displacement_pct": 44.6,
      "targets_high_displacement": false
    },
    {
      "operator_root": "BATTALION",
      "total_properties": 63,
      "total_acquisitions": 92,
      "llc_count": 3,
      "llc_entities": [
        "BATTALION FUNDING LLC",
        "BATTALION LENDING LLC",
        "BATTALION MORTGAGE LLC"
      ],
      "total_portfolio_value": 0,
      "avg_acquisition_price": 0.0,
      "acquisitions_per_month": 9.02,
      "first_acquisition": "2025-04-17",
      "last_acquisition": "2026-02-17",
      "zip_codes_targeted": [
        "10453",
        "10455",
        "10456",
        "10458",
        "10465",
        "10472",
        "10474",
        "11207",
        "11208",
        "11212",
        "11213",
        "11216",
        "11217",
        "11221",
        "11233",
        "11237",
        "11421",
        "11433"
      ],
      "high_displacement_acquisitions": 38,
      "high_displacement_pct": 41.3,
      "targets_high_displacement": false
    },
    {
      "operator_root": "METROPOLITAN",
      "total_properties": 62,
      "total_acquisitions": 63,
      "llc_count": 11,
      "llc_entities": [
        "5549 METROPOLITAN LLC",
        "C1 METROPOLITAN AVE LLC",
        "C2 METROPOLITAN AVE LLC",
        "EE METROPOLITAN LLC",
        "HC METROPOLITAN LLC",
        "METROPOLITAN COMERCIAL BANK",
        "METROPOLITAN COMMERCIAL BANK",
        "METROPOLITAN COMMERCIAL BANK ISAOA",
        "METROPOLITAN LIFE INSURANCE COMPANY",
        "METROPOLITAN NATIONAL BANK MORTGAGE COMPANY LLC",
        "METROPOLITAN TOWER LIFE INSURANCE COMPANY"
      ],
      "total_portfolio_value": 2418243.76,
      "avg_acquisition_price": 38384.82,
      "acquisitions_per_month": 5.62,
      "first_acquisition": "2025-04-16",
      "last_acquisition": "2026-03-18",
      "zip_codes_targeted": [
        "10001",
        "10002",
        "10003",
        "10007",
        "10012",
        "10013",
        "10035",
        "10453",
        "10457",
        "10460",
        "10466",
        "11101",
        "11201",
        "11203",
        "11204",
        "11205",
        "11213",
        "11221",
        "11222",
        "11225",
        "11354",
        "11369",
        "11385",
        "11418",
        "11430",
        "11436"
      ],
      "high_displacement_acquisitions": 21,
      "high_displacement_pct": 33.3,
      "targets_high_displacement": false
    },
    {
      "operator_root": "VALLEY",
      "total_properties": 57,
      "total_acquisitions": 74,
      "llc_count": 6,
      "llc_entities": [
        "NORTH VALLEY CAPITAL LLC",
        "S VALLEY 104 LLC",
        "VALLEY NATIONAL BANK",
        "VALLEY NATIONAL BANK ISAOA ATIMA",
        "VALLEY NATIONAL BANK NA",
        "VALLEY ROAD HOLDINGS LLC"
      ],
      "total_portfolio_value": 7255500.0,
      "avg_acquisition_price": 98047.3,
      "acquisitions_per_month": 6.73,
      "first_acquisition": "2025-04-28",
      "last_acquisition": "2026-03-24",
      "zip_codes_targeted": [
        "10001",
        "10002",
        "10009",
        "10014",
        "10031",
        "10035",
        "10452",
        "10453",
        "10454",
        "10457",
        "10463",
        "10468",
        "10473",
        "11201",
        "11203",
        "11205",
        "11212",
        "11215",
        "11216",
        "11221",
        "11249"
      ],
      "high_displacement_acquisitions": 30,
      "high_displacement_pct": 40.5,
      "targets_high_displacement": false
    },
    {
      "operator_root": "COMMUNITY",
      "total_properties": 56,
      "total_acquisitions": 64,
      "llc_count": 9,
      "llc_entities": [
        "COMMUNITY BANK NATIONAL ASSOCIATION",
        "COMMUNITY FEDERAL SAVINGS BANK",
        "COMMUNITY FEDERAL SAVINGS BANK ISAOA",
        "COMMUNITY FEDERAL SAVINGS BANK ISAOA/ATIMA",
        "COMMUNITY LOAN SERVICING LLC",
        "FIRST COMMUNITY BANK",
        "NORTHEAST COMMUNITY BANK",
        "THE COMMUNITY PRESERVATION CORPORATION",
        "THE COMMUNITY PRESERVATION CORPORTION"
      ],
      "total_portfolio_value": 0,
      "avg_acquisition_price": 0.0,
      "acquisitions_per_month": 5.89,
      "first_acquisition": "2025-05-01",
      "last_acquisition": "2026-03-23",
      "zip_codes_targeted": [
        "10010",
        "10012",
        "10013",
        "10021",
        "10024",
        "10025",
        "10028",
        "10034",
        "10128",
        "10462",
        "10463",
        "10468",
        "11102",
        "11205",
        "11206",
        "11212",
        "11213",
        "11215",
        "11216",
        "11218",
        "11221",
        "11222",
        "11229",
        "11230",
        "11233",
        "11234",
        "11237",
        "11249",
        "11355",
        "11368",
        "11374",
        "11385",
        "11418"
      ],
      "high_displacement_acquisitions": 31,
      "high_displacement_pct": 48.4,
      "targets_high_displacement": false
    },
    {
      "operator_root": "STANDARD",
      "total_properties": 52,
      "total_acquisitions": 90,
      "llc_count": 4,
      "llc_entities": [
        "STANDARD FEDERAL BANK FSB",
        "STANDARD INSURANCE COMAPNY",
        "STANDARD INSURANCE COMPANY",
        "STANDARD INSURANCE COMPANY AN OREGON CORPORATION"
      ],
      "total_portfolio_value": 0,
      "avg_acquisition_price": 0.0,
      "acquisitions_per_month": 8.68,
      "first_acquisition": "2025-04-22",
      "last_acquisition": "2026-02-27",
      "zip_codes_targeted": [
        "10019",
        "10452",
        "10453",
        "10455",
        "10456",
        "10457",
        "10458",
        "10459",
        "10460",
        "10462",
        "10463",
        "10467",
        "10468",
        "10473",
        "11103",
        "11207",
        "11212",
        "11215",
        "11226",
        "11233",
        "11415"
      ],
      "high_displacement_acquisitions": 53,
      "high_displacement_pct": 58.9,
      "targets_high_displacement": true
    },
    {
      "operator_root": "RIDGEWOOD",
      "total_properties": 48,
      "total_acquisitions": 50,
      "llc_count": 11,
      "llc_entities": [
        "232 RIDGEWOOD AVE CORP",
        "407 RIDGEWOOD AVE LLC",
        "510 RIDGEWOOD AVE CORP",
        "6702 RIDGEWOOD LLC",
        "RIDGEWOOD 407 LLC",
        "RIDGEWOOD 781 LLC A NEW YORK",
        "RIDGEWOOD LOFTS LLC",
        "RIDGEWOOD SAVING BANK",
        "RIDGEWOOD SAVINGS BANK",
        "RIDGEWOOD SAVINGS BANK ISAOA",
        "RIDGEWOOD SAVINGS BANK ISAOA/ATIMA"
      ],
      "total_portfolio_value": 5289325.0,
      "avg_acquisition_price": 105786.5,
      "acquisitions_per_month": 5.1,
      "first_acquisition": "2025-04-18",
      "last_acquisition": "2026-02-06",
      "zip_codes_targeted": [
        "10001",
        "10033",
        "10452",
        "10457",
        "10458",
        "10459",
        "10462",
        "11201",
        "11206",
        "11207",
        "11208",
        "11211",
        "11217",
        "11219",
        "11221",
        "11222",
        "11225",
        "11230",
        "11233",
        "11237",
        "11385",
        "11419",
        "11422",
        "11429",
        "11432"
      ],
      "high_displacement_acquisitions": 28,
      "high_displacement_pct": 56.0,
      "targets_high_displacement": true
    },
    {
      "operator_root": "BROAD",
      "total_properties": 43,
      "total_acquisitions": 76,
      "llc_count": 3,
      "llc_entities": [
        "BROAD X FUNDING II LLC",
        "BROAD X FUNDING III LLC",
        "BROAD X FUNDING LLC"
      ],
      "total_portfolio_value": 0,
      "avg_acquisition_price": 0.0,
      "acquisitions_per_month": 6.79,
      "first_acquisition": "2025-04-23",
      "last_acquisition": "2026-03-25",
      "zip_codes_targeted": [
        "10452",
        "10453",
        "10456",
        "10457",
        "10458",
        "10460",
        "10467",
        "10468",
        "10469",
        "10472",
        "11201",
        "11207",
        "11212",
        "11216",
        "11221"
      ],
      "high_displacement_acquisitions": 41,
      "high_displacement_pct": 53.9,
      "targets_high_displacement": true
    },
    {
      "operator_root": "HABIB",
      "total_properties": 40,
      "total_acquisitions": 45,
      "llc_count": 10,
      "llc_entities": [
        "HABIB AHSAN",
        "HABIB AMERICAN BANK",
        "HABIB AMERICAN BANK A/K/A HAB BANK",
        "HABIB AMERICAN BANK AKA HAB BANK",
        "HABIB AMERICAN BANK ISAOA/ATIMA",
        "HABIB AYESHA",
        "HABIB BANK",
        "HABIB MOHAMMAD A",
        "HABIB SHAHINA",
        "HABIB SHIMUL"
      ],
      "total_portfolio_value": 3957000.0,
      "avg_acquisition_price": 87933.33,
      "acquisitions_per_month": 4.18,
      "first_acquisition": "2025-04-14",
      "last_acquisition": "2026-03-03",
      "zip_codes_targeted": [
        "10001",
        "10013",
        "10034",
        "10457",
        "10458",
        "10472",
        "10473",
        "11101",
        "11203",
        "11207",
        "11211",
        "11212",
        "11214",
        "11216",
        "11217",
        "11221",
        "11233",
        "11362",
        "11427",
        "11428",
        "11432",
        "11434"
      ],
      "high_displacement_acquisitions": 28,
      "high_displacement_pct": 62.2,
      "targets_high_displacement": true
    },
    {
      "operator_root": "BROADVIEW",
      "total_properties": 39,
      "total_acquisitions": 42,
      "llc_count": 3,
      "llc_entities": [
        "BROADVIEW CAPITAL LLC",
        "BROADVIEW CAPITAL LLC ISAOA ATIMA",
        "BROADVIEW CAPITAL LLC ISAOA/ATIMA"
      ],
      "total_portfolio_value": 0,
      "avg_acquisition_price": 0.0,
      "acquisitions_per_month": 3.83,
      "first_acquisition": "2025-04-24",
      "last_acquisition": "2026-03-19",
      "zip_codes_targeted": [
        "10460",
        "10461",
        "11205",
        "11206",
        "11211",
        "11212",
        "11216",
        "11221",
        "11226",
        "11233",
        "11385"
      ],
      "high_displacement_acquisitions": 14,
      "high_displacement_pct": 33.3,
      "targets_high_displacement": false
    },
    {
      "operator_root": "MTEK",
      "total_properties": 37,
      "total_acquisitions": 37,
      "llc_count": 9,
      "llc_entities": [
        "MTEK 174 JEFFERSON LLC",
        "MTEK CAPITAL LLC",
        "MTEK FORT GREENE LLC",
        "MTEK FRANKLIN LLC",
        "MTEK FULTON LLC",
        "MTEK GOLD LLC",
        "MTEK NYC LLC",
        "MTEK PARK LLC",
        "MTEK UNION LLC"
      ],
      "total_portfolio_value": 37661442.5,
      "avg_acquisition_price": 1017876.82,
      "acquisitions_per_month": 3.46,
      "first_acquisition": "2025-04-29",
      "last_acquisition": "2026-03-16",
      "zip_codes_targeted": [
        "11203",
        "11207",
        "11208",
        "11216",
        "11217",
        "11221",
        "11434"
      ],
      "high_displacement_acquisitions": 12,
      "high_displacement_pct": 32.4,
      "targets_high_displacement": false
    },
    {
      "operator_root": "SYMETRA",
      "total_properties": 36,
      "total_acquisitions": 52,
      "llc_count": 4,
      "llc_entities": [
        "SYMETRA LIFE INSURANCE",
        "SYMETRA LIFE INSURANCE COMPANY",
        "SYMETRA LIFE INSURANCE COMPANY AN IOWA CORP",
        "SYMETRA NATIONAL LIFE INSURANCE COMPANY"
      ],
      "total_portfolio_value": 0,
      "avg_acquisition_price": 0.0,
      "acquisitions_per_month": 4.95,
      "first_acquisition": "2025-04-28",
      "last_acquisition": "2026-03-09",
      "zip_codes_targeted": [
        "10011",
        "10012",
        "10013",
        "10014",
        "10022",
        "10028",
        "10453",
        "10456",
        "10460",
        "10463",
        "11207",
        "11209",
        "11212",
        "11226",
        "11228",
        "11233",
        "11385",
        "11432"
      ],
      "high_displacement_acquisitions": 28,
      "high_displacement_pct": 53.8,
      "targets_high_displacement": true
    },
    {
      "operator_root": "CROSS",
      "total_properties": 35,
      "total_acquisitions": 37,
      "llc_count": 9,
      "llc_entities": [
        "2104 CROSS BRONX LLC",
        "2775 CROSS BRONX EXPY LLC",
        "8005 CROSS ISLAND LLC",
        "CROSS 2024-H2 MORTGAGE TRUST",
        "CROSS COUNTRY MORTGAGE LLC",
        "CROSS COUNTY SAVINGS BANK",
        "CROSS NAOMI ELDORA",
        "CROSS RIVER BANK",
        "CROSS RIVER BANK NA"
      ],
      "total_portfolio_value": 4495000.0,
      "avg_acquisition_price": 121486.49,
      "acquisitions_per_month": 3.35,
      "first_acquisition": "2025-04-23",
      "last_acquisition": "2026-03-20",
      "zip_codes_targeted": [
        "10017",
        "10021",
        "10030",
        "10031",
        "10039",
        "10465",
        "10466",
        "10472",
        "11204",
        "11212",
        "11213",
        "11221",
        "11225",
        "11226",
        "11426"
      ],
      "high_displacement_acquisitions": 15,
      "high_displacement_pct": 40.5,
      "targets_high_displacement": false
    },
    {
      "operator_root": "ARBOR",
      "total_properties": 35,
      "total_acquisitions": 48,
      "llc_count": 8,
      "llc_entities": [
        "ARBOR AGENCY LENDING LLC",
        "ARBOR ATLAS SD FUNDING LLC",
        "ARBOR CH FUNDING LLC",
        "ARBOR COMMERCIAL FUNDING I LLC",
        "ARBOR COMMERCIAL FUNDING I LLC ISAOA /ATIMA",
        "ARBOR REALTY PARTICIPATION LLC",
        "ARBOR REALTY SR INC",
        "ARBOR ROW LLC"
      ],
      "total_portfolio_value": 0,
      "avg_acquisition_price": 0.0,
      "acquisitions_per_month": 4.34,
      "first_acquisition": "2025-04-25",
      "last_acquisition": "2026-03-23",
      "zip_codes_targeted": [
        "10010",
        "10012",
        "10013",
        "10016",
        "10021",
        "10025",
        "10036",
        "10458",
        "10460",
        "10461",
        "10468",
        "11101",
        "11210",
        "11213",
        "11214",
        "11215",
        "11216",
        "11222",
        "11225",
        "11226",
        "11230",
        "11232",
        "11235"
      ],
      "high_displacement_acquisitions": 29,
      "high_displacement_pct": 60.4,
      "targets_high_displacement": true
    },
    {
      "operator_root": "DERBY",
      "total_properties": 34,
      "total_acquisitions": 54,
      "llc_count": 8,
      "llc_entities": [
        "DERBY 538 LLC",
        "DERBY BOW 9 LLC",
        "DERBY DENVER 303 LENDER II LLC",
        "DERBY FIG HOLDINGS 1 LP",
        "DERBY FIG HOLDINGS I LLC",
        "DERBY ROADRUNNER 355 LLC",
        "DERBY SLED 580 LLC",
        "DERBY WRIGHT 1571 LLC"
      ],
      "total_portfolio_value": 7225500.0,
      "avg_acquisition_price": 133805.56,
      "acquisitions_per_month": 5.08,
      "first_acquisition": "2025-05-05",
      "last_acquisition": "2026-03-20",
      "zip_codes_targeted": [
        "10001",
        "10011",
        "10014",
        "10018",
        "10038",
        "10075",
        "11104",
        "11201",
        "11205",
        "11206",
        "11213",
        "11215",
        "11217",
        "11222",
        "11231",
        "11232",
        "11233",
        "11249",
        "11385"
      ],
      "high_displacement_acquisitions": 19,
      "high_displacement_pct": 35.2,
      "targets_high_displacement": false
    }
  ]
}